{"is_source_file": true, "format": "JavaScript (React JSX)", "description": "This file defines a React functional component 'Quiz' that renders a five-question quiz interface, manages state for user inputs, and handles submission to update the application store and navigate to recommendations. It also includes utility functions for confetti animation and state initialization.", "external_files": ["../components/common/Container", "../components/common/Card", "../components/common/Button", "../components/common/Progress", "../state/hooks"], "external_methods": ["useStore"], "published": ["default"], "classes": [], "methods": [{"name": "Quiz()", "description": "React component for the quiz interface, managing user input, state initialization, and submission handling.", "scope": "", "scopeKind": ""}, {"name": "sparkConfetti()", "description": "Function to generate confetti animation overlay upon quiz submission.", "scope": "Quiz", "scopeKind": "function"}, {"name": "handleSubmit", "description": "Async function to handle form submission: saves responses, triggers confetti, and redirects to recommendations."}, {"name": "toggleInterest", "description": "Function to toggle interests in the multi-select interest chips."}, {"name": "step()", "scope": "Quiz.sparkConfetti", "scopeKind": "function", "description": "unavailable"}], "calls": ["useStore", "setQuiz", "window.matchMedia", "document.createElement", "requestAnimationFrame", "cancelAnimationFrame", "document.body.appendChild", "canvas.getContext", "canvas.parentNode.removeChild", "setTimeout"], "search-terms": ["Quiz.jsx", "confetti animation", "useStore hook", "5-question quiz", "React form state", "interest chips toggle", "confetti confetti", "submit handler"], "state": 2, "file_id": 21, "knowledge_revision": 116, "git_revision": "5faf0ccad6bab71d478077baed33cee54dce95a5", "revision_history": [{"45": ""}, {"75": "d35508435f254404c184c745e870f47cd83f6fb4"}, {"84": "2bf705c21388da641d59096178952bd24345e804"}, {"87": "2bf705c21388da641d59096178952bd24345e804"}, {"94": "0e28c3d2116b7ef0e2669a80f97d16d5c3b35330"}, {"105": "384b9c9150e36565f3ee9eee308867619e1584ea"}, {"106": "384b9c9150e36565f3ee9eee308867619e1584ea"}, {"107": "384b9c9150e36565f3ee9eee308867619e1584ea"}, {"116": "5faf0ccad6bab71d478077baed33cee54dce95a5"}], "ctags": [{"_type": "tag", "name": "1", "path": "/home/kavia/workspace/code-generation/teamsync-engage-182304-182313/team_sync_frontend/src/pages/Quiz.jsx", "pattern": "/^              aria-valuemin={1}$/", "language": "JavaScript", "kind": "field", "scope": "aria", "scopeKind": "class"}, {"_type": "tag", "name": "1", "path": "/home/kavia/workspace/code-generation/teamsync-engage-182304-182313/team_sync_frontend/src/pages/Quiz.jsx", "pattern": "/^              min={1}$/", "language": "JavaScript", "kind": "field", "scope": "min", "scopeKind": "class"}, {"_type": "tag", "name": "1", "path": "/home/kavia/workspace/code-generation/teamsync-engage-182304-182313/team_sync_frontend/src/pages/Quiz.jsx", "pattern": "/^              step={1}$/", "language": "JavaScript", "kind": "field", "scope": "step", "scopeKind": "class"}, {"_type": "tag", "name": "15", "path": "/home/kavia/workspace/code-generation/teamsync-engage-182304-182313/team_sync_frontend/src/pages/Quiz.jsx", "pattern": "/^              aria-valuemin={15}$/", "language": "JavaScript", "kind": "field", "scope": "aria", "scopeKind": "class"}, {"_type": "tag", "name": "15", "path": "/home/kavia/workspace/code-generation/teamsync-engage-182304-182313/team_sync_frontend/src/pages/Quiz.jsx", "pattern": "/^              min={15}$/", "language": "JavaScript", "kind": "field", "scope": "min", "scopeKind": "class"}, {"_type": "tag", "name": "15", "path": "/home/kavia/workspace/code-generation/teamsync-engage-182304-182313/team_sync_frontend/src/pages/Quiz.jsx", "pattern": "/^              step={15}$/", "language": "JavaScript", "kind": "field", "scope": "step", "scopeKind": "class"}, {"_type": "tag", "name": "180", "path": "/home/kavia/workspace/code-generation/teamsync-engage-182304-182313/team_sync_frontend/src/pages/Quiz.jsx", "pattern": "/^              aria-valuemax={180}$/", "language": "JavaScript", "kind": "field", "scope": "aria", "scopeKind": "class"}, {"_type": "tag", "name": "180", "path": "/home/kavia/workspace/code-generation/teamsync-engage-182304-182313/team_sync_frontend/src/pages/Quiz.jsx", "pattern": "/^              max={180}$/", "language": "JavaScript", "kind": "field", "scope": "max", "scopeKind": "class"}, {"_type": "tag", "name": "5", "path": "/home/kavia/workspace/code-generation/teamsync-engage-182304-182313/team_sync_frontend/src/pages/Quiz.jsx", "pattern": "/^              aria-valuemax={5}$/", "language": "JavaScript", "kind": "field", "scope": "aria", "scopeKind": "class"}, {"_type": "tag", "name": "5", "path": "/home/kavia/workspace/code-generation/teamsync-engage-182304-182313/team_sync_frontend/src/pages/Quiz.jsx", "pattern": "/^              max={5}$/", "language": "JavaScript", "kind": "field", "scope": "max", "scopeKind": "class"}, {"_type": "tag", "name": "Quiz", "path": "/home/kavia/workspace/code-generation/teamsync-engage-182304-182313/team_sync_frontend/src/pages/Quiz.jsx", "pattern": "/^export default function Quiz() {$/", "language": "JavaScript", "kind": "function", "signature": "()"}, {"_type": "tag", "name": "btn ${budget === 'high' ? '' : 'secondary'}", "path": "/home/kavia/workspace/code-generation/teamsync-engage-182304-182313/team_sync_frontend/src/pages/Quiz.jsx", "pattern": "/^              <label className={`btn ${budget === 'high' ? '' : 'secondary'}`}>$/", "language": "JavaScript", "kind": "field", "scope": "AnonymousClass008c35800401", "scopeKind": "class"}, {"_type": "tag", "name": "btn ${budget === 'medium' ? '' : 'secondary'}", "path": "/home/kavia/workspace/code-generation/teamsync-engage-182304-182313/team_sync_frontend/src/pages/Quiz.jsx", "pattern": "/^              <label className={`btn ${budget === 'medium' ? '' : 'secondary'}`}>$/", "language": "JavaScript", "kind": "field", "scope": "AnonymousClass008c35800301", "scopeKind": "class"}, {"_type": "tag", "name": "btn ${energy === 'balanced' ? '' : 'secondary'}", "path": "/home/kavia/workspace/code-generation/teamsync-engage-182304-182313/team_sync_frontend/src/pages/Quiz.jsx", "pattern": "/^              <label className={`btn ${energy === 'balanced' ? '' : 'secondary'}`}>$/", "language": "JavaScript", "kind": "field", "scope": "AnonymousClass008c35800101", "scopeKind": "class"}, {"_type": "tag", "name": "btn ${energy === 'high' ? '' : 'secondary'}", "path": "/home/kavia/workspace/code-generation/teamsync-engage-182304-182313/team_sync_frontend/src/pages/Quiz.jsx", "pattern": "/^              <label className={`btn ${energy === 'high' ? '' : 'secondary'}`}>$/", "language": "JavaScript", "kind": "field", "scope": "AnonymousClass008c35800201", "scopeKind": "class"}, {"_type": "tag", "name": "budget", "path": "/home/kavia/workspace/code-generation/teamsync-engage-182304-182313/team_sync_frontend/src/pages/Quiz.jsx", "pattern": "/^                  checked={budget === 'high'}$/", "language": "JavaScript", "kind": "property", "scope": "checked", "scopeKind": "class"}, {"_type": "tag", "name": "budget", "path": "/home/kavia/workspace/code-generation/teamsync-engage-182304-182313/team_sync_frontend/src/pages/Quiz.jsx", "pattern": "/^                  checked={budget === 'low'}$/", "language": "JavaScript", "kind": "property", "scope": "checked", "scopeKind": "class"}, {"_type": "tag", "name": "budget", "path": "/home/kavia/workspace/code-generation/teamsync-engage-182304-182313/team_sync_frontend/src/pages/Quiz.jsx", "pattern": "/^                  checked={budget === 'medium'}$/", "language": "JavaScript", "kind": "property", "scope": "checked", "scopeKind": "class"}, {"_type": "tag", "name": "checked", "path": "/home/kavia/workspace/code-generation/teamsync-engage-182304-182313/team_sync_frontend/src/pages/Quiz.jsx", "pattern": "/^                  checked={budget === 'high'}$/", "language": "JavaScript", "kind": "class"}, {"_type": "tag", "name": "checked", "path": "/home/kavia/workspace/code-generation/teamsync-engage-182304-182313/team_sync_frontend/src/pages/Quiz.jsx", "pattern": "/^                  checked={budget === 'low'}$/", "language": "JavaScript", "kind": "class"}, {"_type": "tag", "name": "checked", "path": "/home/kavia/workspace/code-generation/teamsync-engage-182304-182313/team_sync_frontend/src/pages/Quiz.jsx", "pattern": "/^                  checked={budget === 'medium'}$/", "language": "JavaScript", "kind": "class"}, {"_type": "tag", "name": "checked", "path": "/home/kavia/workspace/code-generation/teamsync-engage-182304-182313/team_sync_frontend/src/pages/Quiz.jsx", "pattern": "/^                  checked={energy === 'balanced'}$/", "language": "JavaScript", "kind": "class"}, {"_type": "tag", "name": "checked", "path": "/home/kavia/workspace/code-generation/teamsync-engage-182304-182313/team_sync_frontend/src/pages/Quiz.jsx", "pattern": "/^                  checked={energy === 'chill'}$/", "language": "JavaScript", "kind": "class", "scope": "Quiz", "scopeKind": "class"}, {"_type": "tag", "name": "checked", "path": "/home/kavia/workspace/code-generation/teamsync-engage-182304-182313/team_sync_frontend/src/pages/Quiz.jsx", "pattern": "/^                  checked={energy === 'high'}$/", "language": "JavaScript", "kind": "class"}, {"_type": "tag", "name": "collaboration", "path": "/home/kavia/workspace/code-generation/teamsync-engage-182304-182313/team_sync_frontend/src/pages/Quiz.jsx", "pattern": "/^              aria-valuenow={collaboration}$/", "language": "JavaScript", "kind": "field", "scope": "aria", "scopeKind": "class"}, {"_type": "tag", "name": "collaboration", "path": "/home/kavia/workspace/code-generation/teamsync-engage-182304-182313/team_sync_frontend/src/pages/Quiz.jsx", "pattern": "/^              value={collaboration}$/", "language": "JavaScript", "kind": "field", "scope": "value", "scopeKind": "class"}, {"_type": "tag", "name": "duration", "path": "/home/kavia/workspace/code-generation/teamsync-engage-182304-182313/team_sync_frontend/src/pages/Quiz.jsx", "pattern": "/^              aria-valuenow={duration}$/", "language": "JavaScript", "kind": "field", "scope": "aria", "scopeKind": "class"}, {"_type": "tag", "name": "duration", "path": "/home/kavia/workspace/code-generation/teamsync-engage-182304-182313/team_sync_frontend/src/pages/Quiz.jsx", "pattern": "/^              value={duration}$/", "language": "JavaScript", "kind": "field", "scope": "value", "scopeKind": "class"}, {"_type": "tag", "name": "energy", "path": "/home/kavia/workspace/code-generation/teamsync-engage-182304-182313/team_sync_frontend/src/pages/Quiz.jsx", "pattern": "/^                  checked={energy === 'balanced'}$/", "language": "JavaScript", "kind": "property", "scope": "checked", "scopeKind": "class"}, {"_type": "tag", "name": "energy", "path": "/home/kavia/workspace/code-generation/teamsync-engage-182304-182313/team_sync_frontend/src/pages/Quiz.jsx", "pattern": "/^                  checked={energy === 'chill'}$/", "language": "JavaScript", "kind": "property", "scope": "Quiz.checked", "scopeKind": "class"}, {"_type": "tag", "name": "energy", "path": "/home/kavia/workspace/code-generation/teamsync-engage-182304-182313/team_sync_frontend/src/pages/Quiz.jsx", "pattern": "/^                  checked={energy === 'high'}$/", "language": "JavaScript", "kind": "property", "scope": "checked", "scopeKind": "class"}, {"_type": "tag", "name": "sparkConfetti", "path": "/home/kavia/workspace/code-generation/teamsync-engage-182304-182313/team_sync_frontend/src/pages/Quiz.jsx", "pattern": "/^  function sparkConfetti() {$/", "language": "JavaScript", "kind": "function", "signature": "()", "scope": "Quiz", "scopeKind": "function"}, {"_type": "tag", "name": "step", "path": "/home/kavia/workspace/code-generation/teamsync-engage-182304-182313/team_sync_frontend/src/pages/Quiz.jsx", "pattern": "/^    function step() {$/", "language": "JavaScript", "kind": "function", "signature": "()", "scope": "Quiz.sparkConfetti", "scopeKind": "function"}], "hash": "1b5fcafcd0e377fbe18e3b9bfbfd0095", "format-version": 4, "code-base-name": "team_sync_frontend", "filename": "team_sync_frontend/src/pages/Quiz.jsx", "fields": [{"name": "aria-valuemin={1}", "scope": "aria", "scopeKind": "class", "description": "unavailable"}, {"name": "min={1}", "scope": "min", "scopeKind": "class", "description": "unavailable"}, {"name": "step={1}", "scope": "step", "scopeKind": "class", "description": "unavailable"}, {"name": "aria-valuemin={15}", "scope": "aria", "scopeKind": "class", "description": "unavailable"}, {"name": "min={15}", "scope": "min", "scopeKind": "class", "description": "unavailable"}, {"name": "step={15}", "scope": "step", "scopeKind": "class", "description": "unavailable"}, {"name": "aria-valuemax={180}", "scope": "aria", "scopeKind": "class", "description": "unavailable"}, {"name": "max={180}", "scope": "max", "scopeKind": "class", "description": "unavailable"}, {"name": "aria-valuemax={5}", "scope": "aria", "scopeKind": "class", "description": "unavailable"}, {"name": "max={5}", "scope": "max", "scopeKind": "class", "description": "unavailable"}, {"name": "<label className={`btn ${budget === 'high' ? '' : 'secondary'}`}>", "scope": "AnonymousClass008c35800401", "scopeKind": "class", "description": "unavailable"}, {"name": "<label className={`btn ${budget === 'medium' ? '' : 'secondary'}`}>", "scope": "AnonymousClass008c35800301", "scopeKind": "class", "description": "unavailable"}, {"name": "<label className={`btn ${energy === 'balanced' ? '' : 'secondary'}`}>", "scope": "AnonymousClass008c35800101", "scopeKind": "class", "description": "unavailable"}, {"name": "<label className={`btn ${energy === 'high' ? '' : 'secondary'}`}>", "scope": "AnonymousClass008c35800201", "scopeKind": "class", "description": "unavailable"}, {"name": "checked={budget === 'high'}", "scope": "checked", "scopeKind": "class", "description": "unavailable"}, {"name": "checked={budget === 'low'}", "scope": "checked", "scopeKind": "class", "description": "unavailable"}, {"name": "checked={budget === 'medium'}", "scope": "checked", "scopeKind": "class", "description": "unavailable"}, {"name": "aria-valuenow={collaboration}", "scope": "aria", "scopeKind": "class", "description": "unavailable"}, {"name": "value={collaboration}", "scope": "value", "scopeKind": "class", "description": "unavailable"}, {"name": "aria-valuenow={duration}", "scope": "aria", "scopeKind": "class", "description": "unavailable"}, {"name": "value={duration}", "scope": "value", "scopeKind": "class", "description": "unavailable"}, {"name": "checked={energy === 'balanced'}", "scope": "checked", "scopeKind": "class", "description": "unavailable"}, {"name": "checked={energy === 'chill'}", "scope": "Quiz.checked", "scopeKind": "class", "description": "unavailable"}, {"name": "checked={energy === 'high'}", "scope": "checked", "scopeKind": "class", "description": "unavailable"}]}